ensapp/__init__.py
ensapp/ensapp.py
ensapp/ensapp_classes.py
ensapp-0.0.2.dist-info/METADATA
ensapp-0.0.2.dist-info/WHEEL
ensapp-0.0.2.dist-info/RECORD
