Metadata-Version: 2.1
Name: ensapp
Version: 0.0.2
Summary: Communicate With Ensapp Website.
Author: Abdellah Elidrissi (AE)
Author-email: abdellah20.elidrissi20@gmail.com
Requires-Python: >=3.6,<4.0
Classifier: Programming Language :: Python :: 3
Classifier: Programming Language :: Python :: 3.6
Classifier: Programming Language :: Python :: 3.7
Classifier: Programming Language :: Python :: 3.8
Classifier: Programming Language :: Python :: 3.9
Classifier: Programming Language :: Python :: 3.10
Classifier: Programming Language :: Python :: 3.11
Classifier: Programming Language :: Python :: 3.12
